alice/__init__.py
alice/alice.py
pyalice/__init__.py
pyalice/pyalice.py
py.alice-0.1.dist-info/METADATA
py.alice-0.1.dist-info/WHEEL
py.alice-0.1.dist-info/top_level.txt
py.alice-0.1.dist-info/RECORD
