Metadata-Version: 2.1
Name: py.alice
Version: 0.1
Summary: Yandex.Dialogs non-official package.
Home-page: https://github.com/Jornau/alice
Author: Alexander Surkov
Author-email: jornau@yandex.ru
License: MIT
Keywords: yandex dialogs alice skills
Platform: UNKNOWN
Classifier: Development Status :: 3 - Alpha
Classifier: License :: OSI Approved :: MIT License
Classifier: Programming Language :: Python :: 3.7
Classifier: Topic :: Software Development :: Libraries :: Python Modules
Requires-Dist: requests
